[
  {
    "teamName": "Slam Dunkers",
    "gameType": "Basketball",
    "coach": "Sarah Thompson",
    "captain": "David Davis",
    "players": "Kobe Bryant, Tracy McGrady, Jason Richardson, etc.",
    "homeVenue": "Arena Center",
    "league": "National Basketball Association (NBA)",
    "championshipsWon": 3,
    "foundedYear": 1985,
    "websiteURL": "www.slamdunkers.com",
    "logoURL": "https://img.lovepik.com/free-png/20211209/lovepik-male-silhouette-slam-dunk-png-image_401425944_wh1200.png"
  },
  {
    "teamName": "Thunder Strikers",
    "gameType": "Baseball",
    "coach": "Robert Anderson",
    "captain": "Emily Roberts",
    "players": "Andy Abad, Chance Adams, Lane Adams, etc.",
    "homeVenue": "Diamond Park",
    "league": "Major League Baseball (MLB)",
    "championshipsWon": 7,
    "foundedYear": 1901,
    "websiteURL": "www.thunderstrikers.com",
    "logoURL": "https://p.kindpng.com/picc/s/713-7134459_thunder-logo-png-thunder-baseball-logo-png-transparent.png"
  },
  {
    "teamName": "Ice Breakers",
    "gameType": "Hockey",
    "coach": "Peter Wilson",
    "captain": "Thomas Adams",
    "players": "Declan Conway, Steven Fowler, Parker Moskal, etc.",
    "homeVenue": "Ice Arena",
    "league": "National Hockey League (NHL)",
    "championshipsWon": 4,
    "foundedYear": 1995,
    "websiteURL": "www.icebreakers.com",
    "logoURL": "https://www.seekpng.com/png/detail/785-7854642_ice-breakers-hockey-logo.png"
  },
  {
    "teamName": "New York Yankees",
    "gameType": "Baseball",
    "coach": "Aaron Boone",
    "captain": "Aaron Judge",
    "players": "Aaron Judge, Giancarlo Stanton, Gerrit Cole, etc.",
    "homeVenue": "Yankee Stadium",
    "league": "Major League Baseball (MLB)",
    "championshipsWon": 27,
    "foundedYear": 1901,
    "websiteURL": "https://www.mlb.com/yankees",
    "logoURL": "https://logos-world.net/wp-content/uploads/2020/05/New-York-Yankees-Symbol.png"
  },
  {
    "teamName": "FC United",
    "gameType": "Soccer",
    "coach": "John Smith",
    "captain": "Michael Johnson",
    "players": "Paul Ennis, Michael Donohue , Curtis Jones, etc.",
    "homeVenue": "City Stadium",
    "league": "Premier League",
    "championshipsWon": 5,
    "foundedYear": 1990,
    "websiteURL": "www.fcunited.com",
    "logoURL": "https://www.clipartmax.com/png/middle/283-2830784_fc-united-f-c-united-of-manchester.png"
  },
  {
    "teamName": "Los Angeles Lakers",
    "gameType": "Basketball",
    "coach": "Frank Vogel",
    "captain": "LeBron James",
    "players": "Anthony Davis, Russell Westbrook, Kentavious Caldwell-Pope, etc.",
    "homeVenue": "Crypto.com Arena",
    "league": "National Basketball Association (NBA)",
    "championshipsWon": 17,
    "foundedYear": 1947,
    "websiteURL": "https://www.nba.com/lakers/",
    "logoURL": "https://assets.stickpng.com/images/62066c74d7b91b0004122607.png"
  },
  {
    "teamName": "FC Barcelona",
    "gameType": "Football (Soccer)",
    "coach": "Ronald Koeman",
    "captain": "Sergio Busquets",
    "players": "Lionel Messi, Antoine Griezmann, Frenkie de Jong, etc.",
    "homeVenue": "Camp Nou",
    "league": "La Liga",
    "championshipsWon": 31,
    "foundedYear": 1899,
    "websiteURL": "https://www.fcbarcelona.com/",
    "logoURL": "https://logos-world.net/wp-content/uploads/2020/04/Barcelona-Logo.png"
  },
  {
    "teamName": "Real Madrid CF",
    "gameType": "Football (Soccer)",
    "coach": "Carlo Ancelotti",
    "captain": "Sergio Ramos (formerly), Marcelo",
    "players": "Karim Benzema, Eden Hazard, Luka Modric, etc.",
    "homeVenue": "Santiago Bernabeu Stadium",
    "league": "La Liga",
    "championshipsWon": 47,
    "foundedYear": 1902,
    "websiteURL": "https://www.realmadrid.com/",
    "logoURL": "https://logos-world.net/wp-content/uploads/2020/06/Real-Madrid-symbol.png"
  },
  {
    "teamName": "Golden State Warriors",
    "gameType": "Basketball",
    "coach": "Steve Kerr",
    "captain": "Stephen Curry",
    "players": "Klay Thompson, Draymond Green, etc.",
    "homeVenue": "Chase Center",
    "league": "National Basketball Association (NBA)",
    "championshipsWon": 6,
    "foundedYear": 1946,
    "websiteURL": "www.nba.com/warriors",
    "logoURL": "https://content.sportslogos.net/news/2019/06/golden-state-warriors-logo.png"
  },
  {
    "teamName": "New England Revolution",
    "gameType": "Soccer",
    "coach": "Bruce Arena",
    "captain": "Carles Gil",
    "players": "Gustavo Bou, Matt Turner, etc.",
    "homeVenue": "Gillette Stadium",
    "league": "Major League Soccer (MLS)",
    "championshipsWon": 0,
    "foundedYear": 1994,
    "websiteURL": "www.revolutionsoccer.net",
    "logoURL": "https://images.mlssoccer.com/image/private/t_editorial_landscape_12_desktop/prd-league/lnu28ws6yri5l09gjftn.png"
  }
]
